streamfy/__init__.py
streamfy/frontend/dist/index.html
streamfy/frontend/dist/css/app.193d5172.css
streamfy/frontend/dist/css/chunk-vendors.32a03c52.css
streamfy/frontend/dist/js/app.d81a86a4.js
streamfy/frontend/dist/js/app.d81a86a4.js.map
streamfy/frontend/dist/js/chunk-vendors.8d96e6e0.js
streamfy/frontend/dist/js/chunk-vendors.8d96e6e0.js.map
streamfy-0.3.5.dist-info/LICENSE
streamfy-0.3.5.dist-info/METADATA
streamfy-0.3.5.dist-info/WHEEL
streamfy-0.3.5.dist-info/top_level.txt
streamfy-0.3.5.dist-info/RECORD
