Metadata-Version: 2.1
Name: streamfy
Version: 0.3.5
Summary: Modern frontend web components based on Buefy for Streamlit.
Home-page: https://github.com/hal9ai/streamfy
Author: Javier Luraschi
Author-email: jluraschi@gmail.com
License: UNKNOWN
Platform: UNKNOWN
Requires-Python: >=3.6
License-File: LICENSE
Requires-Dist: streamlit (>=0.63)
